[
  {
    "ContainingType": "AssignmentManagement.Api.Controllers.AssignmentsController",
    "Method": "ListAll",
    "RelativePath": "api/Assignments",
    "HttpMethod": "GET",
    "IsController": true,
    "Order": 0,
    "Parameters": [],
    "ReturnTypes": []
  },
  {
    "ContainingType": "AssignmentManagement.Api.Controllers.AssignmentsController",
    "Method": "CreateAssignment",
    "RelativePath": "api/Assignments",
    "HttpMethod": "POST",
    "IsController": true,
    "Order": 0,
    "Parameters": [
      {
        "Name": "assignment",
        "Type": "AssignmentManagement.Core.Assignment",
        "IsRequired": true
      }
    ],
    "ReturnTypes": []
  },
  {
    "ContainingType": "AssignmentManagement.Api.Controllers.AssignmentsController",
    "Method": "Delete",
    "RelativePath": "api/Assignments/{title}",
    "HttpMethod": "DELETE",
    "IsController": true,
    "Order": 0,
    "Parameters": [
      {
        "Name": "title",
        "Type": "System.String",
        "IsRequired": true
      }
    ],
    "ReturnTypes": []
  },
  {
    "ContainingType": "AssignmentManagement.Api.Controllers.AssignmentsController",
    "Method": "FindByTitle",
    "RelativePath": "api/Assignments/title",
    "HttpMethod": "GET",
    "IsController": true,
    "Order": 0,
    "Parameters": [
      {
        "Name": "title",
        "Type": "System.String",
        "IsRequired": false
      }
    ],
    "ReturnTypes": []
  },
  {
    "ContainingType": "AssignmentManagement.Api.Controllers.WeatherForecastController",
    "Method": "Get",
    "RelativePath": "WeatherForecast",
    "HttpMethod": "GET",
    "IsController": true,
    "Order": 0,
    "Parameters": [],
    "ReturnTypes": [
      {
        "Type": "System.Collections.Generic.IEnumerable\u00601[[AssignmentManagement.Api.WeatherForecast, AssignmentManagement.Api, Version=1.0.0.0, Culture=neutral, PublicKeyToken=null]]",
        "MediaTypes": [
          "text/plain",
          "application/json",
          "text/json"
        ],
        "StatusCode": 200
      }
    ],
    "EndpointName": "GetWeatherForecast"
  }
]